[{"col":1,"course":"音乐","row":3},{"col":2,"course":"音乐","row":3},{"col":3,"course":"语文","row":3},{"col":4,"course":"体育","row":3},{"col":5,"course":"体育","row":3},{"col":6,"course":"语文","row":3},{"col":7,"course":"英文","row":3},{"col":8,"course":"体育","row":3},{"col":9,"course":"语文","row":3},{"col":10,"course":"语文","row":3},{"col":11,"course":"英文","row":3},{"col":12,"course":"音乐","row":3},{"col":13,"course":"音乐","row":3},{"col":14,"course":"信息技术","row":3},{"col":15,"course":"体育","row":3},{"col":16,"course":"体育","row":3},{"col":17,"course":"数学","row":3},{"col":18,"course":"音乐","row":3},{"col":19,"course":"英文","row":3},{"col":20,"course":"体育","row":3},{"col":21,"course":"音乐","row":3},{"col":22,"course":"英文","row":3},{"col":23,"course":"体育","row":3},{"col":24,"course":"英文","row":3},{"col":25,"course":"语文","row":3},{"col":26,"course":"音乐","row":3},{"col":27,"course":"语文","row":3},{"col":28,"course":"体育","row":3},{"col":29,"course":"数学","row":3},{"col":30,"course":"体育","row":3},{"col":31,"course":"体育","row":3},{"col":32,"course":"数学","row":3},{"col":33,"course":"信息技术","row":3},{"col":34,"course":"音乐","row":3},{"col":35,"course":"数学","row":3},{"col":36,"course":"数学","row":3},{"col":37,"course":"体育","row":3},{"col":38,"course":"音乐","row":3},{"col":39,"course":"信息技术","row":3},{"col":40,"course":"体育","row":3},{"col":41,"course":"英文","row":3},{"col":42,"course":"数学","row":3},{"col":43,"course":"信息技术","row":3},{"col":44,"course":"体育","row":3},{"col":45,"course":"语文","row":3},{"col":46,"course":"语文","row":3},{"col":47,"course":"音乐","row":3},{"col":48,"course":"音乐","row":3},{"col":49,"course":"语文","row":3},{"col":50,"course":"音乐","row":3},{"col":51,"course":"语文","row":3},{"col":52,"course":"信息技术","row":3},{"col":53,"course":"信息技术","row":3},{"col":54,"course":"音乐","row":3},{"col":55,"course":"信息技术","row":3},{"col":56,"course":"体育","row":3},{"col":1,"course":"信息技术","row":4},{"col":2,"course":"音乐","row":4},{"col":3,"course":"英文","row":4},{"col":4,"course":"音乐","row":4},{"col":5,"course":"语文","row":4},{"col":6,"course":"英文","row":4},{"col":7,"course":"数学","row":4},{"col":8,"course":"数学","row":4},{"col":9,"course":"体育","row":4},{"col":10,"course":"数学","row":4},{"col":11,"course":"体育","row":4},{"col":12,"course":"语文","row":4},{"col":13,"course":"英文","row":4},{"col":14,"course":"语文","row":4},{"col":15,"course":"数学","row":4},{"col":16,"course":"音乐","row":4},{"col":17,"course":"信息技术","row":4},{"col":18,"course":"音乐","row":4},{"col":19,"course":"信息技术","row":4},{"col":20,"course":"音乐","row":4},{"col":21,"course":"信息技术","row":4},{"col":22,"course":"音乐","row":4},{"col":23,"course":"英文","row":4},{"col":24,"course":"数学","row":4},{"col":25,"course":"体育","row":4},{"col":26,"course":"数学","row":4},{"col":27,"course":"音乐","row":4},{"col":28,"course":"数学","row":4},{"col":29,"course":"数学","row":4},{"col":30,"course":"信息技术","row":4},{"col":31,"course":"英文","row":4},{"col":32,"course":"信息技术","row":4},{"col":33,"course":"体育","row":4},{"col":34,"course":"信息技术","row":4},{"col":35,"course":"英文","row":4},{"col":36,"course":"音乐","row":4},{"col":37,"course":"数学","row":4},{"col":38,"course":"信息技术","row":4},{"col":39,"course":"数学","row":4},{"col":40,"course":"数学","row":4},{"col":41,"course":"音乐","row":4},{"col":42,"course":"英文","row":4},{"col":43,"course":"英文","row":4},{"col":44,"course":"体育","row":4},{"col":45,"course":"音乐","row":4},{"col":46,"course":"语文","row":4},{"col":47,"course":"信息技术","row":4},{"col":48,"course":"数学","row":4},{"col":49,"course":"语文","row":4},{"col":50,"course":"信息技术","row":4},{"col":51,"course":"数学","row":4},{"col":52,"course":"语文","row":4},{"col":53,"course":"体育","row":4},{"col":54,"course":"体育","row":4},{"col":55,"course":"数学","row":4},{"col":56,"course":"信息技术","row":4},{"col":1,"course":"音乐","row":5},{"col":2,"course":"数学","row":5},{"col":3,"course":"语文","row":5},{"col":4,"course":"体育","row":5},{"col":5,"course":"语文","row":5},{"col":6,"course":"英文","row":5},{"col":7,"course":"信息技术","row":5},{"col":8,"course":"语文","row":5},{"col":9,"course":"英文","row":5},{"col":10,"course":"语文","row":5},{"col":11,"course":"语文","row":5},{"col":12,"course":"体育","row":5},{"col":13,"course":"语文","row":5},{"col":14,"course":"音乐","row":5},{"col":15,"course":"信息技术","row":5},{"col":16,"course":"语文","row":5},{"col":17,"course":"体育","row":5},{"col":18,"course":"体育","row":5},{"col":19,"course":"信息技术","row":5},{"col":20,"course":"音乐","row":5},{"col":21,"course":"英文","row":5},{"col":22,"course":"数学","row":5},{"col":23,"course":"音乐","row":5},{"col":24,"course":"数学","row":5},{"col":25,"course":"语文","row":5},{"col":26,"course":"英文","row":5},{"col":27,"course":"信息技术","row":5},{"col":28,"course":"音乐","row":5},{"col":29,"course":"音乐","row":5},{"col":30,"course":"语文","row":5},{"col":31,"course":"数学","row":5},{"col":32,"course":"语文","row":5},{"col":33,"course":"体育","row":5},{"col":34,"course":"信息技术","row":5},{"col":35,"course":"音乐","row":5},{"col":36,"course":"信息技术","row":5},{"col":37,"course":"英文","row":5},{"col":38,"course":"体育","row":5},{"col":39,"course":"数学","row":5},{"col":40,"course":"体育","row":5},{"col":41,"course":"数学","row":5},{"col":42,"course":"语文","row":5},{"col":43,"course":"音乐","row":5},{"col":44,"course":"信息技术","row":5},{"col":45,"course":"体育","row":5},{"col":46,"course":"信息技术","row":5},{"col":47,"course":"信息技术","row":5},{"col":48,"course":"数学","row":5},{"col":49,"course":"语文","row":5},{"col":50,"course":"英文","row":5},{"col":51,"course":"英文","row":5},{"col":52,"course":"音乐","row":5},{"col":53,"course":"音乐","row":5},{"col":54,"course":"音乐","row":5},{"col":55,"course":"语文","row":5},{"col":56,"course":"数学","row":5},{"col":1,"course":"体育","row":6},{"col":2,"course":"信息技术","row":6},{"col":3,"course":"数学","row":6},{"col":4,"course":"语文","row":6},{"col":5,"course":"语文","row":6},{"col":6,"course":"数学","row":6},{"col":7,"course":"音乐","row":6},{"col":8,"course":"数学","row":6},{"col":9,"course":"英文","row":6},{"col":10,"course":"语文","row":6},{"col":11,"course":"语文","row":6},{"col":12,"course":"体育","row":6},{"col":13,"course":"数学","row":6},{"col":14,"course":"信息技术","row":6},{"col":15,"course":"音乐","row":6},{"col":16,"course":"音乐","row":6},{"col":17,"course":"语文","row":6},{"col":18,"course":"信息技术","row":6},{"col":19,"course":"英文","row":6},{"col":20,"course":"体育","row":6},{"col":21,"course":"体育","row":6},{"col":22,"course":"信息技术","row":6},{"col":23,"course":"英文","row":6},{"col":24,"course":"英文","row":6},{"col":25,"course":"数学","row":6},{"col":26,"course":"音乐","row":6},{"col":27,"course":"信息技术","row":6},{"col":28,"course":"数学","row":6},{"col":29,"course":"语文","row":6},{"col":30,"course":"数学","row":6},{"col":31,"course":"信息技术","row":6},{"col":32,"course":"信息技术","row":6},{"col":33,"course":"信息技术","row":6},{"col":34,"course":"语文","row":6},{"col":35,"course":"英文","row":6},{"col":36,"course":"音乐","row":6},{"col":37,"course":"英文","row":6},{"col":38,"course":"语文","row":6},{"col":39,"course":"信息技术","row":6},{"col":40,"course":"体育","row":6},{"col":41,"course":"音乐","row":6},{"col":42,"course":"英文","row":6},{"col":43,"course":"体育","row":6},{"col":44,"course":"语文","row":6},{"col":45,"course":"英文","row":6},{"col":46,"course":"语文","row":6},{"col":47,"course":"数学","row":6},{"col":48,"course":"英文","row":6},{"col":49,"course":"语文","row":6},{"col":50,"course":"音乐","row":6},{"col":51,"course":"音乐","row":6},{"col":52,"course":"语文","row":6},{"col":53,"course":"信息技术","row":6},{"col":54,"course":"信息技术","row":6},{"col":55,"course":"体育","row":6},{"col":56,"course":"信息技术","row":6},{"col":1,"course":"音乐","row":7},{"col":2,"course":"音乐","row":7},{"col":3,"course":"信息技术","row":7},{"col":4,"course":"体育","row":7},{"col":5,"course":"英文","row":7},{"col":6,"course":"语文","row":7},{"col":7,"course":"体育","row":7},{"col":8,"course":"英文","row":7},{"col":9,"course":"信息技术","row":7},{"col":10,"course":"音乐","row":7},{"col":11,"course":"信息技术","row":7},{"col":12,"course":"英文","row":7},{"col":13,"course":"体育","row":7},{"col":14,"course":"音乐","row":7},{"col":15,"course":"数学","row":7},{"col":16,"course":"音乐","row":7},{"col":17,"course":"英文","row":7},{"col":18,"course":"数学","row":7},{"col":19,"course":"语文","row":7},{"col":20,"course":"信息技术","row":7},{"col":21,"course":"信息技术","row":7},{"col":22,"course":"语文","row":7},{"col":23,"course":"英文","row":7},{"col":24,"course":"语文","row":7},{"col":25,"course":"音乐","row":7},{"col":26,"course":"音乐","row":7},{"col":27,"course":"体育","row":7},{"col":28,"course":"英文","row":7},{"col":29,"course":"数学","row":7},{"col":30,"course":"语文","row":7},{"col":31,"course":"信息技术","row":7},{"col":32,"course":"信息技术","row":7},{"col":33,"course":"数学","row":7},{"col":34,"course":"数学","row":7},{"col":35,"course":"音乐","row":7},{"col":36,"course":"数学","row":7},{"col":37,"course":"数学","row":7},{"col":38,"course":"音乐","row":7},{"col":39,"course":"信息技术","row":7},{"col":40,"course":"数学","row":7},{"col":41,"course":"语文","row":7},{"col":42,"course":"体育","row":7},{"col":43,"course":"数学","row":7},{"col":44,"course":"信息技术","row":7},{"col":45,"course":"语文","row":7},{"col":46,"course":"音乐","row":7},{"col":47,"course":"英文","row":7},{"col":48,"course":"数学","row":7},{"col":49,"course":"数学","row":7},{"col":50,"course":"数学","row":7},{"col":51,"course":"体育","row":7},{"col":52,"course":"语文","row":7},{"col":53,"course":"数学","row":7},{"col":54,"course":"英文","row":7},{"col":55,"course":"体育","row":7},{"col":56,"course":"体育","row":7},{"col":1,"course":"英文","row":8},{"col":2,"course":"体育","row":8},{"col":3,"course":"英文","row":8},{"col":4,"course":"语文","row":8},{"col":5,"course":"语文","row":8},{"col":6,"course":"信息技术","row":8},{"col":7,"course":"语文","row":8},{"col":8,"course":"体育","row":8},{"col":9,"course":"英文","row":8},{"col":10,"course":"英文","row":8},{"col":11,"course":"音乐","row":8},{"col":12,"course":"数学","row":8},{"col":13,"course":"语文","row":8},{"col":14,"course":"音乐","row":8},{"col":15,"course":"信息技术","row":8},{"col":16,"course":"数学","row":8},{"col":17,"course":"音乐","row":8},{"col":18,"course":"体育","row":8},{"col":19,"course":"信息技术","row":8},{"col":20,"course":"语文","row":8},{"col":21,"course":"语文","row":8},{"col":22,"course":"信息技术","row":8},{"col":23,"course":"信息技术","row":8},{"col":24,"course":"语文","row":8},{"col":25,"course":"体育","row":8},{"col":26,"course":"英文","row":8},{"col":27,"course":"信息技术","row":8},{"col":28,"course":"语文","row":8},{"col":29,"course":"语文","row":8},{"col":30,"course":"英文","row":8},{"col":31,"course":"英文","row":8},{"col":32,"course":"体育","row":8},{"col":33,"course":"音乐","row":8},{"col":34,"course":"英文","row":8},{"col":35,"course":"音乐","row":8},{"col":36,"course":"语文","row":8},{"col":37,"course":"体育","row":8},{"col":38,"course":"体育","row":8},{"col":39,"course":"语文","row":8},{"col":40,"course":"数学","row":8},{"col":41,"course":"信息技术","row":8},{"col":42,"course":"音乐","row":8},{"col":43,"course":"语文","row":8},{"col":44,"course":"信息技术","row":8},{"col":45,"course":"音乐","row":8},{"col":46,"course":"英文","row":8},{"col":47,"course":"信息技术","row":8},{"col":48,"course":"英文","row":8},{"col":49,"course":"语文","row":8},{"col":50,"course":"信息技术","row":8},{"col":51,"course":"体育","row":8},{"col":52,"course":"语文","row":8},{"col":53,"course":"体育","row":8},{"col":54,"course":"英文","row":8},{"col":55,"course":"信息技术","row":8},{"col":56,"course":"体育","row":8},{"col":1,"course":"体育","row":9},{"col":2,"course":"语文","row":9},{"col":3,"course":"语文","row":9},{"col":4,"course":"信息技术","row":9},{"col":5,"course":"体育","row":9},{"col":6,"course":"音乐","row":9},{"col":7,"course":"音乐","row":9},{"col":8,"course":"数学","row":9},{"col":9,"course":"音乐","row":9},{"col":10,"course":"信息技术","row":9},{"col":11,"course":"音乐","row":9},{"col":12,"course":"语文","row":9},{"col":13,"course":"数学","row":9},{"col":14,"course":"信息技术","row":9},{"col":15,"course":"音乐","row":9},{"col":16,"course":"数学","row":9},{"col":17,"course":"体育","row":9},{"col":18,"course":"英文","row":9},{"col":19,"course":"音乐","row":9},{"col":20,"course":"音乐","row":9},{"col":21,"course":"信息技术","row":9},{"col":22,"course":"语文","row":9},{"col":23,"course":"数学","row":9},{"col":24,"course":"英文","row":9},{"col":25,"course":"体育","row":9},{"col":26,"course":"信息技术","row":9},{"col":27,"course":"数学","row":9},{"col":28,"course":"音乐","row":9},{"col":29,"course":"英文","row":9},{"col":30,"course":"音乐","row":9},{"col":31,"course":"英文","row":9},{"col":32,"course":"语文","row":9},{"col":33,"course":"语文","row":9},{"col":34,"course":"信息技术","row":9},{"col":35,"course":"数学","row":9},{"col":36,"course":"音乐","row":9},{"col":37,"course":"数学","row":9},{"col":38,"course":"体育","row":9},{"col":39,"course":"数学","row":9},{"col":40,"course":"信息技术","row":9},{"col":41,"course":"语文","row":9},{"col":42,"course":"体育","row":9},{"col":43,"course":"英文","row":9},{"col":44,"course":"数学","row":9},{"col":45,"course":"数学","row":9},{"col":46,"course":"体育","row":9},{"col":47,"course":"信息技术","row":9},{"col":48,"course":"体育","row":9},{"col":49,"course":"体育","row":9},{"col":50,"course":"语文","row":9},{"col":51,"course":"音乐","row":9},{"col":52,"course":"语文","row":9},{"col":53,"course":"信息技术","row":9},{"col":54,"course":"英文","row":9},{"col":55,"course":"音乐","row":9},{"col":56,"course":"信息技术","row":9},{"col":1,"course":"数学","row":10},{"col":2,"course":"音乐","row":10},{"col":3,"course":"信息技术","row":10},{"col":4,"course":"信息技术","row":10},{"col":5,"course":"音乐","row":10},{"col":6,"course":"英文","row":10},{"col":7,"course":"英文","row":10},{"col":8,"course":"信息技术","row":10},{"col":9,"course":"数学","row":10},{"col":10,"course":"英文","row":10},{"col":11,"course":"数学","row":10},{"col":12,"course":"音乐","row":10},{"col":13,"course":"语文","row":10},{"col":14,"course":"语文","row":10},{"col":15,"course":"数学","row":10},{"col":16,"course":"数学","row":10},{"col":17,"course":"信息技术","row":10},{"col":18,"course":"语文","row":10},{"col":19,"course":"音乐","row":10},{"col":20,"course":"体育","row":10},{"col":21,"course":"信息技术","row":10},{"col":22,"course":"数学","row":10},{"col":23,"course":"音乐","row":10},{"col":24,"course":"体育","row":10},{"col":25,"course":"信息技术","row":10},{"col":26,"course":"语文","row":10},{"col":27,"course":"英文","row":10},{"col":28,"course":"信息技术","row":10},{"col":29,"course":"语文","row":10},{"col":30,"course":"数学","row":10},{"col":31,"course":"英文","row":10},{"col":32,"course":"英文","row":10},{"col":33,"course":"英文","row":10},{"col":34,"course":"音乐","row":10},{"col":35,"course":"体育","row":10},{"col":36,"course":"语文","row":10},{"col":37,"course":"语文","row":10},{"col":38,"course":"音乐","row":10},{"col":39,"course":"信息技术","row":10},{"col":40,"course":"音乐","row":10},{"col":41,"course":"音乐","row":10},{"col":42,"course":"体育","row":10},{"col":43,"course":"音乐","row":10},{"col":44,"course":"音乐","row":10},{"col":45,"course":"音乐","row":10},{"col":46,"course":"语文","row":10},{"col":47,"course":"音乐","row":10},{"col":48,"course":"体育","row":10},{"col":49,"course":"信息技术","row":10},{"col":50,"course":"体育","row":10},{"col":51,"course":"数学","row":10},{"col":52,"course":"信息技术","row":10},{"col":53,"course":"音乐","row":10},{"col":54,"course":"体育","row":10},{"col":55,"course":"数学","row":10},{"col":56,"course":"英文","row":10}]
